[{"rozvrhovaAkce":[{"roakIdno":283394,"nazev":"Mezinárodní vztahy","katedra":"KPF","predmet":"0449","statut":"A","ucitIdno":2758,"ucitel":{"ucitIdno":2758,"jmeno":"Lukáš","prijmeni":"Novotný","titulPred":"Mgr.","titulZa":"Ph.D. M.A.","platnost":"A","zamestnanec":"A"},"rok":"2016","budova":"MF","mistnost":"2.28","kapacitaMistnosti":190,"planObsazeni":90,"obsazeni":60,"typAkce":"Cvičení","typAkceZkr":"Cv","semestr":"ZS","platnost":"A","den":"Pondělí","denZkr":"Po","hodinaOd":12,"hodinaDo":13,"hodinaSkutOd":{"value":"18:00"},"hodinaSkutDo":{"value":"19:50"},"tydenOd":39,"tydenDo":51,"tyden":"Každý","tydenZkr":"K","grupIdno":null,"jeNadrazena":"N","maNadrazenou":"N","kontakt":"Automaticky vygenerovaná apost. akce","krouzky":"3.AJ SV VZ,3.FI-P0,3.FI-SV,3.GEOPO bc,3.GEOSV bc,3.HI-PO,3.HV SV VZ,3.Hi-SV,3.NJ-PO,3.NJ-SV,3.NJ-SV V,3.PO-SV,3.TV SV O,3.TV SV VZ,3.VV SV SN,3.ČJ SV O,3.ČJ SV VZ","casovaRada":"UJEP","datum":null,"datumOd":{"value":"26.9.2016"},"datumDo":{"value":"19.12.2016"},"druhAkce":"R","vsichniUciteleUcitIdno":"2758","vsichniUciteleJmenaTituly":"Mgr. Lukáš Novotný, Ph.D. M.A.","vsichniUcitelePrijmeni":"Novotný","referencedIdno":283394,"poznamkaRozvrhare":null,"nekonaSe":null,"owner":"RSBERANOVA","zakazaneAkce":null,"vyucJazyk":"CZ"},{"roakIdno":286276,"nazev":"Geografie modelového regionu","katedra":"KGEO","predmet":"P421","statut":"A","ucitIdno":1633,"ucitel":{"ucitIdno":1633,"jmeno":"Ivan","prijmeni":"Bičík","titulPred":"doc. RNDr.","titulZa":"CSc.","platnost":"A","zamestnanec":"A"},"rok":"2016","budova":"CS","mistnost":"402","kapacitaMistnosti":40,"planObsazeni":30,"obsazeni":18,"typAkce":"Přednáška","typAkceZkr":"Př","semestr":"ZS","platnost":"A","den":"Středa","denZkr":"St","hodinaOd":4,"hodinaDo":4,"hodinaSkutOd":{"value":"10:00"},"hodinaSkutDo":{"value":"10:50"},"tydenOd":40,"tydenDo":51,"tyden":"Každý","tydenZkr":"K","grupIdno":null,"jeNadrazena":"N","maNadrazenou":"N","kontakt":"Automaticky vygenerovaná apost. akce","krouzky":"3.BIGEO bc,3.GEOHI bc,3.GEOINFbc,3.GEONJ bc,3.GEOPO bc,3.GEOSV bc,3.GEOTV bc,3.MAGEO bc","casovaRada":"UJEP","datum":null,"datumOd":{"value":"5.10.2016"},"datumDo":{"value":"21.12.2016"},"druhAkce":"R","vsichniUciteleUcitIdno":"1633","vsichniUciteleJmenaTituly":"doc. RNDr. Ivan Bičík, CSc.","vsichniUcitelePrijmeni":"Bičík","referencedIdno":286276,"poznamkaRozvrhare":null,"nekonaSe":null,"owner":"PETRUSPRF","zakazaneAkce":null,"vyucJazyk":null},{"roakIdno":286277,"nazev":"Geografie modelového regionu","katedra":"KGEO","predmet":"P421","statut":"A","ucitIdno":1633,"ucitel":{"ucitIdno":1633,"jmeno":"Ivan","prijmeni":"Bičík","titulPred":"doc. RNDr.","titulZa":"CSc.","platnost":"A","zamestnanec":"A"},"rok":"2016","budova":"CS","mistnost":"402","kapacitaMistnosti":40,"planObsazeni":30,"obsazeni":18,"typAkce":"Cvičení","typAkceZkr":"Cv","semestr":"ZS","platnost":"A","den":"Středa","denZkr":"St","hodinaOd":5,"hodinaDo":6,"hodinaSkutOd":{"value":"11:00"},"hodinaSkutDo":{"value":"12:50"},"tydenOd":40,"tydenDo":51,"tyden":"Každý","tydenZkr":"K","grupIdno":null,"jeNadrazena":"N","maNadrazenou":"N","kontakt":"Automaticky vygenerovaná apost. akce","krouzky":"3.BIGEO bc,3.GEOHI bc,3.GEOINFbc,3.GEONJ bc,3.GEOPO bc,3.GEOSV bc,3.GEOTV bc,3.MAGEO bc","casovaRada":"UJEP","datum":null,"datumOd":{"value":"5.10.2016"},"datumDo":{"value":"21.12.2016"},"druhAkce":"R","vsichniUciteleUcitIdno":"1633","vsichniUciteleJmenaTituly":"doc. RNDr. Ivan Bičík, CSc.","vsichniUcitelePrijmeni":"Bičík","referencedIdno":286277,"poznamkaRozvrhare":null,"nekonaSe":null,"owner":"PETRUSPRF","zakazaneAkce":null,"vyucJazyk":null},{"roakIdno":283283,"nazev":"Dějiny politického myšlení IV","katedra":"KPF","predmet":"0430","statut":"A","ucitIdno":1824,"ucitel":{"ucitIdno":1824,"jmeno":"Rudolf","prijmeni":"Kučera","titulPred":"doc. PhDr.","titulZa":"CSc.","platnost":"A","zamestnanec":"A"},"rok":"2016","budova":"FF","mistnost":"A 204","kapacitaMistnosti":77,"planObsazeni":40,"obsazeni":20,"typAkce":"Přednáška","typAkceZkr":"Př","semestr":"ZS","platnost":"A","den":"Středa","denZkr":"St","hodinaOd":5,"hodinaDo":6,"hodinaSkutOd":{"value":"11:00"},"hodinaSkutDo":{"value":"12:50"},"tydenOd":40,"tydenDo":51,"tyden":"Každý","tydenZkr":"K","grupIdno":null,"jeNadrazena":"N","maNadrazenou":"N","kontakt":"Automaticky vygenerovaná apost. akce","krouzky":"3.FI-P0,3.GEOPO bc,3.HI-PO,3.NJ-PO,3.PO-SV","casovaRada":"UJEP","datum":null,"datumOd":{"value":"5.10.2016"},"datumDo":{"value":"21.12.2016"},"druhAkce":"R","vsichniUciteleUcitIdno":"1824","vsichniUciteleJmenaTituly":"doc. PhDr. Rudolf Kučera, CSc.","vsichniUcitelePrijmeni":"Kučera","referencedIdno":283283,"poznamkaRozvrhare":null,"nekonaSe":null,"owner":"RSBERANOVA","zakazaneAkce":null,"vyucJazyk":"CZ"},{"roakIdno":286293,"nazev":"Vývoj geografického myšlení","katedra":"KGEO","predmet":"P522","statut":"A","ucitIdno":920,"ucitel":{"ucitIdno":920,"jmeno":"Ladislav","prijmeni":"Skokan","titulPred":"doc. RNDr.","titulZa":"CSc.","platnost":"A","zamestnanec":"A"},"rok":"2016","budova":"CS","mistnost":"407","kapacitaMistnosti":23,"planObsazeni":25,"obsazeni":19,"typAkce":"Přednáška","typAkceZkr":"Př","semestr":"ZS","platnost":"A","den":"Středa","denZkr":"St","hodinaOd":9,"hodinaDo":10,"hodinaSkutOd":{"value":"15:00"},"hodinaSkutDo":{"value":"16:50"},"tydenOd":40,"tydenDo":51,"tyden":"Každý","tydenZkr":"K","grupIdno":null,"jeNadrazena":"N","maNadrazenou":"N","kontakt":"Automaticky vygenerovaná apost. akce","krouzky":"3.BIGEO bc,3.GEOHI bc,3.GEOINFbc,3.GEONJ bc,3.GEOPO bc,3.GEOSV bc,3.GEOTV bc,3.MAGEO bc","casovaRada":"UJEP","datum":null,"datumOd":{"value":"5.10.2016"},"datumDo":{"value":"21.12.2016"},"druhAkce":"R","vsichniUciteleUcitIdno":"920","vsichniUciteleJmenaTituly":"doc. RNDr. Ladislav Skokan, CSc.","vsichniUcitelePrijmeni":"Skokan","referencedIdno":286293,"poznamkaRozvrhare":null,"nekonaSe":null,"owner":"PETRUSPRF","zakazaneAkce":null,"vyucJazyk":null},{"roakIdno":283285,"nazev":"Dějiny politického myšlení V","katedra":"KPF","predmet":"0435","statut":"A","ucitIdno":3266,"ucitel":{"ucitIdno":3266,"jmeno":"Jiří","prijmeni":"Chotaš","titulPred":"PhDr. Ing.","titulZa":"Ph.D.","platnost":"A","zamestnanec":"A"},"rok":"2016","budova":"FF","mistnost":"A 118","kapacitaMistnosti":77,"planObsazeni":40,"obsazeni":20,"typAkce":"Přednáška","typAkceZkr":"Př","semestr":"ZS","platnost":"A","den":"Čtvrtek","denZkr":"Čt","hodinaOd":11,"hodinaDo":12,"hodinaSkutOd":{"value":"17:00"},"hodinaSkutDo":{"value":"18:50"},"tydenOd":39,"tydenDo":51,"tyden":"Každý","tydenZkr":"K","grupIdno":null,"jeNadrazena":"N","maNadrazenou":"N","kontakt":"Automaticky vygenerovaná apost. akce","krouzky":"3.FI-P0,3.GEOPO bc,3.HI-PO,3.NJ-PO,3.PO-SV","casovaRada":"UJEP","datum":null,"datumOd":{"value":"29.9.2016"},"datumDo":{"value":"22.12.2016"},"druhAkce":"R","vsichniUciteleUcitIdno":"3266","vsichniUciteleJmenaTituly":"PhDr. Ing. Jiří Chotaš, Ph.D.","vsichniUcitelePrijmeni":"Chotaš","referencedIdno":283285,"poznamkaRozvrhare":null,"nekonaSe":null,"owner":"RSBERANOVA","zakazaneAkce":null,"vyucJazyk":"CZ"},{"roakIdno":283286,"nazev":"Dějiny politického myšlení V","katedra":"KPF","predmet":"0435","statut":"A","ucitIdno":3266,"ucitel":{"ucitIdno":3266,"jmeno":"Jiří","prijmeni":"Chotaš","titulPred":"PhDr. Ing.","titulZa":"Ph.D.","platnost":"A","zamestnanec":"A"},"rok":"2016","budova":"FF","mistnost":"A 118","kapacitaMistnosti":77,"planObsazeni":40,"obsazeni":20,"typAkce":"Cvičení","typAkceZkr":"Cv","semestr":"ZS","platnost":"A","den":"Čtvrtek","denZkr":"Čt","hodinaOd":13,"hodinaDo":13,"hodinaSkutOd":{"value":"19:00"},"hodinaSkutDo":{"value":"19:50"},"tydenOd":39,"tydenDo":51,"tyden":"Každý","tydenZkr":"K","grupIdno":null,"jeNadrazena":"N","maNadrazenou":"N","kontakt":"Automaticky vygenerovaná apost. akce","krouzky":"3.FI-P0,3.GEOPO bc,3.HI-PO,3.NJ-PO,3.PO-SV","casovaRada":"UJEP","datum":null,"datumOd":{"value":"29.9.2016"},"datumDo":{"value":"22.12.2016"},"druhAkce":"R","vsichniUciteleUcitIdno":"3266","vsichniUciteleJmenaTituly":"PhDr. Ing. Jiří Chotaš, Ph.D.","vsichniUcitelePrijmeni":"Chotaš","referencedIdno":283286,"poznamkaRozvrhare":null,"nekonaSe":null,"owner":"RSBERANOVA","zakazaneAkce":null,"vyucJazyk":"CZ"},{"roakIdno":283284,"nazev":"Dějiny politického myšlení IV","katedra":"KPF","predmet":"0430","statut":"A","ucitIdno":3266,"ucitel":{"ucitIdno":3266,"jmeno":"Jiří","prijmeni":"Chotaš","titulPred":"PhDr. Ing.","titulZa":"Ph.D.","platnost":"A","zamestnanec":"A"},"rok":"2016","budova":"FF","mistnost":"B 203","kapacitaMistnosti":28,"planObsazeni":20,"obsazeni":20,"typAkce":"Cvičení","typAkceZkr":"Cv","semestr":"ZS","platnost":"A","den":"Pátek","denZkr":"Pá","hodinaOd":6,"hodinaDo":6,"hodinaSkutOd":{"value":"12:00"},"hodinaSkutDo":{"value":"12:50"},"tydenOd":39,"tydenDo":51,"tyden":"Každý","tydenZkr":"K","grupIdno":null,"jeNadrazena":"N","maNadrazenou":"N","kontakt":"Automaticky vygenerovaná apost. akce","krouzky":"3.FI-P0,3.GEOPO bc,3.HI-PO,3.NJ-PO,3.PO-SV","casovaRada":"UJEP","datum":null,"datumOd":{"value":"30.9.2016"},"datumDo":{"value":"23.12.2016"},"druhAkce":"R","vsichniUciteleUcitIdno":"3266","vsichniUciteleJmenaTituly":"PhDr. Ing. Jiří Chotaš, Ph.D.","vsichniUcitelePrijmeni":"Chotaš","referencedIdno":283284,"poznamkaRozvrhare":null,"nekonaSe":null,"owner":"RSBERANOVA","zakazaneAkce":null,"vyucJazyk":null},{"roakIdno":298917,"nazev":"Evropská integrace","katedra":"KGEO","predmet":"B207","statut":"B","ucitIdno":312,"ucitel":{"ucitIdno":312,"jmeno":"Jiří","prijmeni":"Anděl","titulPred":"doc. RNDr.","titulZa":"CSc.","platnost":"A","zamestnanec":"A"},"rok":"2016","budova":"CS","mistnost":"411","kapacitaMistnosti":30,"planObsazeni":15,"obsazeni":14,"typAkce":"Přednáška","typAkceZkr":"Př","semestr":"LS","platnost":"A","den":"Pondělí","denZkr":"Po","hodinaOd":4,"hodinaDo":5,"hodinaSkutOd":{"value":"10:00"},"hodinaSkutDo":{"value":"11:50"},"tydenOd":7,"tydenDo":20,"tyden":"Každý","tydenZkr":"K","grupIdno":null,"jeNadrazena":"N","maNadrazenou":"N","kontakt":"Automaticky vygenerovaná apost. akce","krouzky":"1. GSE","casovaRada":"UJEP","datum":null,"datumOd":{"value":"13.2.2017"},"datumDo":{"value":"15.5.2017"},"druhAkce":"R","vsichniUciteleUcitIdno":"312","vsichniUciteleJmenaTituly":"doc. RNDr. Jiří Anděl, CSc.","vsichniUcitelePrijmeni":"Anděl","referencedIdno":298917,"poznamkaRozvrhare":null,"nekonaSe":null,"owner":"RSRIEZNER","zakazaneAkce":null,"vyucJazyk":null},{"roakIdno":298994,"nazev":"VK-Právo ve věcech mládeže","katedra":"KGEO","predmet":"0127","statut":"B","ucitIdno":590,"ucitel":{"ucitIdno":590,"jmeno":"Romana","prijmeni":"Vlachová","titulPred":"Mgr.","platnost":"A","zamestnanec":"A"},"rok":"2016","budova":"CS","mistnost":"412","kapacitaMistnosti":20,"planObsazeni":12,"obsazeni":12,"typAkce":"Přednáška","typAkceZkr":"Př","semestr":"LS","platnost":"A","den":"Úterý","denZkr":"Út","hodinaOd":10,"hodinaDo":11,"hodinaSkutOd":{"value":"16:00"},"hodinaSkutDo":{"value":"17:50"},"tydenOd":7,"tydenDo":20,"tyden":"Každý","tydenZkr":"K","grupIdno":null,"jeNadrazena":"N","maNadrazenou":"N","kontakt":"Automaticky vygenerovaná apost. akce","krouzky":null,"casovaRada":"UJEP","datum":null,"datumOd":{"value":"14.2.2017"},"datumDo":{"value":"16.5.2017"},"druhAkce":"R","vsichniUciteleUcitIdno":"590","vsichniUciteleJmenaTituly":"Mgr. Romana Vlachová","vsichniUcitelePrijmeni":"Vlachová","referencedIdno":298994,"poznamkaRozvrhare":null,"nekonaSe":null,"owner":"RSRIEZNER","zakazaneAkce":null,"vyucJazyk":null},{"roakIdno":298988,"nazev":"Aktuální problémy oboru","katedra":"KGEO","predmet":"P622","statut":"A","ucitIdno":1633,"ucitel":{"ucitIdno":1633,"jmeno":"Ivan","prijmeni":"Bičík","titulPred":"doc. RNDr.","titulZa":"CSc.","platnost":"A","zamestnanec":"A"},"rok":"2016","budova":"CS","mistnost":"402","kapacitaMistnosti":40,"planObsazeni":20,"obsazeni":17,"typAkce":"Přednáška","typAkceZkr":"Př","semestr":"LS","platnost":"A","den":"Středa","denZkr":"St","hodinaOd":5,"hodinaDo":6,"hodinaSkutOd":{"value":"11:00"},"hodinaSkutDo":{"value":"12:50"},"tydenOd":7,"tydenDo":20,"tyden":"Každý","tydenZkr":"K","grupIdno":null,"jeNadrazena":"N","maNadrazenou":"N","kontakt":"Automaticky vygenerovaná apost. akce","krouzky":"3.BIGEO bc,3.GEOHI bc,3.GEOINFbc,3.GEONJ bc,3.GEOPO bc,3.GEOSV bc,3.GEOTV bc,3.MAGEO bc","casovaRada":"UJEP","datum":null,"datumOd":{"value":"15.2.2017"},"datumDo":{"value":"17.5.2017"},"druhAkce":"R","vsichniUciteleUcitIdno":"1633","vsichniUciteleJmenaTituly":"doc. RNDr. Ivan Bičík, CSc.","vsichniUcitelePrijmeni":"Bičík","referencedIdno":298988,"poznamkaRozvrhare":null,"nekonaSe":null,"owner":"RSRIEZNER","zakazaneAkce":null,"vyucJazyk":null},{"roakIdno":298989,"nazev":"PVK - Problémové oblasti světa","katedra":"KGEO","predmet":"P626","statut":"B","ucitIdno":1633,"ucitel":{"ucitIdno":1633,"jmeno":"Ivan","prijmeni":"Bičík","titulPred":"doc. RNDr.","titulZa":"CSc.","platnost":"A","zamestnanec":"A"},"rok":"2016","budova":"CS","mistnost":"402","kapacitaMistnosti":40,"planObsazeni":10,"obsazeni":4,"typAkce":"Přednáška","typAkceZkr":"Př","semestr":"LS","platnost":"A","den":"Středa","denZkr":"St","hodinaOd":7,"hodinaDo":7,"hodinaSkutOd":{"value":"13:00"},"hodinaSkutDo":{"value":"13:50"},"tydenOd":7,"tydenDo":20,"tyden":"Každý","tydenZkr":"K","grupIdno":null,"jeNadrazena":"N","maNadrazenou":"N","kontakt":"Automaticky vygenerovaná apost. akce","krouzky":null,"casovaRada":"UJEP","datum":null,"datumOd":{"value":"15.2.2017"},"datumDo":{"value":"17.5.2017"},"druhAkce":"R","vsichniUciteleUcitIdno":"1633","vsichniUciteleJmenaTituly":"doc. RNDr. Ivan Bičík, CSc.","vsichniUcitelePrijmeni":"Bičík","referencedIdno":298989,"poznamkaRozvrhare":null,"nekonaSe":null,"owner":"RSRIEZNER","zakazaneAkce":null,"vyucJazyk":null},{"roakIdno":298990,"nazev":"PVK - Problémové oblasti světa","katedra":"KGEO","predmet":"P626","statut":"B","ucitIdno":1633,"ucitel":{"ucitIdno":1633,"jmeno":"Ivan","prijmeni":"Bičík","titulPred":"doc. RNDr.","titulZa":"CSc.","platnost":"A","zamestnanec":"A"},"rok":"2016","budova":"CS","mistnost":"402","kapacitaMistnosti":40,"planObsazeni":10,"obsazeni":4,"typAkce":"Cvičení","typAkceZkr":"Cv","semestr":"LS","platnost":"A","den":"Středa","denZkr":"St","hodinaOd":8,"hodinaDo":8,"hodinaSkutOd":{"value":"14:00"},"hodinaSkutDo":{"value":"14:50"},"tydenOd":7,"tydenDo":20,"tyden":"Každý","tydenZkr":"K","grupIdno":null,"jeNadrazena":"N","maNadrazenou":"N","kontakt":"Automaticky vygenerovaná apost. akce","krouzky":null,"casovaRada":"UJEP","datum":null,"datumOd":{"value":"15.2.2017"},"datumDo":{"value":"17.5.2017"},"druhAkce":"R","vsichniUciteleUcitIdno":"1633","vsichniUciteleJmenaTituly":"doc. RNDr. Ivan Bičík, CSc.","vsichniUcitelePrijmeni":"Bičík","referencedIdno":298990,"poznamkaRozvrhare":null,"nekonaSe":null,"owner":"RSRIEZNER","zakazaneAkce":null,"vyucJazyk":null},{"roakIdno":296193,"nazev":"Anglický jazyk A","katedra":"KPRF","predmet":"P004","statut":"B","ucitIdno":474,"ucitel":{"ucitIdno":474,"jmeno":"Jaroslav","prijmeni":"Izavčuk","titulPred":"Mgr.","platnost":"A","zamestnanec":"A"},"rok":"2016","budova":"CS","mistnost":"412","kapacitaMistnosti":20,"planObsazeni":40,"obsazeni":16,"typAkce":"Cvičení","typAkceZkr":"Cv","semestr":"LS","platnost":"A","den":"Čtvrtek","denZkr":"Čt","hodinaOd":4,"hodinaDo":5,"hodinaSkutOd":{"value":"10:00"},"hodinaSkutDo":{"value":"11:50"},"tydenOd":7,"tydenDo":20,"tyden":"Každý","tydenZkr":"K","grupIdno":null,"jeNadrazena":"N","maNadrazenou":"N","kontakt":"Automaticky vygenerovaná apost. akce","krouzky":"1.IS","casovaRada":"UJEP","datum":null,"datumOd":{"value":"16.2.2017"},"datumDo":{"value":"18.5.2017"},"druhAkce":"R","vsichniUciteleUcitIdno":"474","vsichniUciteleJmenaTituly":"Mgr. Jaroslav Izavčuk","vsichniUcitelePrijmeni":"Izavčuk","referencedIdno":296193,"poznamkaRozvrhare":null,"nekonaSe":null,"owner":"RREHAKOVA","zakazaneAkce":null,"vyucJazyk":null},{"roakIdno":296304,"nazev":"Současná politická filosofie","katedra":"KPF","predmet":"0423","statut":"A","ucitIdno":3266,"ucitel":{"ucitIdno":3266,"jmeno":"Jiří","prijmeni":"Chotaš","titulPred":"PhDr. Ing.","titulZa":"Ph.D.","platnost":"A","zamestnanec":"A"},"rok":"2016","budova":"MF","mistnost":"01.41","kapacitaMistnosti":90,"planObsazeni":777,"obsazeni":12,"typAkce":"Cvičení","typAkceZkr":"Cv","semestr":"LS","platnost":"A","den":"Pátek","denZkr":"Pá","hodinaOd":2,"hodinaDo":3,"hodinaSkutOd":{"value":"08:00"},"hodinaSkutDo":{"value":"09:50"},"tydenOd":7,"tydenDo":20,"tyden":"Každý","tydenZkr":"K","grupIdno":null,"jeNadrazena":"N","maNadrazenou":"N","kontakt":"Automaticky vygenerovaná apost. akce","krouzky":null,"casovaRada":"UJEP","datum":null,"datumOd":{"value":"17.2.2017"},"datumDo":{"value":"19.5.2017"},"druhAkce":"R","vsichniUciteleUcitIdno":"3266","vsichniUciteleJmenaTituly":"PhDr. Ing. Jiří Chotaš, Ph.D.","vsichniUcitelePrijmeni":"Chotaš","referencedIdno":296304,"poznamkaRozvrhare":null,"nekonaSe":null,"owner":"RMUSIL","zakazaneAkce":null,"vyucJazyk":"CZ"},{"roakIdno":303236,"nazev":"Španělský jazyk - zkouška B","katedra":"CJP","predmet":"0236","statut":"B","ucitIdno":null,"ucitel":null,"rok":"2016","budova":null,"mistnost":null,"kapacitaMistnosti":null,"planObsazeni":777,"obsazeni":3,"typAkce":"Cvičení","typAkceZkr":"Cv","semestr":"LS","platnost":"A","den":null,"denZkr":null,"hodinaOd":null,"hodinaDo":null,"hodinaSkutOd":{"value":"00:00"},"hodinaSkutDo":{"value":"00:00"},"tydenOd":0,"tydenDo":0,"tyden":"Každý","tydenZkr":"K","grupIdno":null,"jeNadrazena":"N","maNadrazenou":"N","kontakt":"Automaticky vygenerovaná apost. akce","krouzky":null,"casovaRada":null,"datum":null,"datumOd":null,"datumDo":null,"druhAkce":"R","vsichniUciteleUcitIdno":"","vsichniUciteleJmenaTituly":"","vsichniUcitelePrijmeni":"","referencedIdno":303236,"poznamkaRozvrhare":null,"nekonaSe":null,"owner":"RJELINKOVA","zakazaneAkce":null,"vyucJazyk":null},{"roakIdno":302573,"nazev":"SZZ - Geografie","katedra":"KGEO","predmet":"SZZ60","statut":"A","ucitIdno":null,"ucitel":null,"rok":"2016","budova":null,"mistnost":null,"kapacitaMistnosti":null,"planObsazeni":777,"obsazeni":8,"typAkce":"Cvičení","typAkceZkr":"Cv","semestr":"LS","platnost":"A","den":null,"denZkr":null,"hodinaOd":null,"hodinaDo":null,"hodinaSkutOd":{"value":"00:00"},"hodinaSkutDo":{"value":"00:00"},"tydenOd":0,"tydenDo":0,"tyden":"Každý","tydenZkr":"K","grupIdno":null,"jeNadrazena":"N","maNadrazenou":"N","kontakt":"Automaticky vygenerovaná apost. akce","krouzky":null,"casovaRada":null,"datum":null,"datumOd":null,"datumDo":null,"druhAkce":"R","vsichniUciteleUcitIdno":"","vsichniUciteleJmenaTituly":"","vsichniUcitelePrijmeni":"","referencedIdno":302573,"poznamkaRozvrhare":null,"nekonaSe":null,"owner":"RSRIEZNER","zakazaneAkce":null,"vyucJazyk":null},{"roakIdno":296453,"nazev":"Politologie","katedra":"KPF","predmet":"SZZ60","statut":"A","ucitIdno":null,"ucitel":null,"rok":"2016","budova":null,"mistnost":null,"kapacitaMistnosti":null,"planObsazeni":777,"obsazeni":17,"typAkce":"Cvičení","typAkceZkr":"Cv","semestr":"LS","platnost":"A","den":null,"denZkr":null,"hodinaOd":null,"hodinaDo":null,"hodinaSkutOd":{"value":"00:00"},"hodinaSkutDo":{"value":"00:00"},"tydenOd":0,"tydenDo":0,"tyden":"Každý","tydenZkr":"K","grupIdno":null,"jeNadrazena":"N","maNadrazenou":"N","kontakt":"Automaticky vygenerovaná apost. akce","krouzky":null,"casovaRada":null,"datum":null,"datumOd":null,"datumDo":null,"druhAkce":"R","vsichniUciteleUcitIdno":"","vsichniUciteleJmenaTituly":"","vsichniUcitelePrijmeni":"","referencedIdno":296453,"poznamkaRozvrhare":null,"nekonaSe":null,"owner":"RMUSIL","zakazaneAkce":null,"vyucJazyk":null},{"roakIdno":300892,"nazev":"Anglický jazyk - zkouška A","katedra":"KPRF","predmet":"P225","statut":"B","ucitIdno":null,"ucitel":null,"rok":"2016","budova":null,"mistnost":null,"kapacitaMistnosti":null,"planObsazeni":777,"obsazeni":56,"typAkce":"Cvičení","typAkceZkr":"Cv","semestr":"LS","platnost":"A","den":null,"denZkr":null,"hodinaOd":null,"hodinaDo":null,"hodinaSkutOd":{"value":"00:00"},"hodinaSkutDo":{"value":"00:00"},"tydenOd":0,"tydenDo":0,"tyden":"Každý","tydenZkr":"K","grupIdno":null,"jeNadrazena":"N","maNadrazenou":"N","kontakt":"Automaticky vygenerovaná apost. akce","krouzky":null,"casovaRada":null,"datum":null,"datumOd":null,"datumDo":null,"druhAkce":"R","vsichniUciteleUcitIdno":"","vsichniUciteleJmenaTituly":"","vsichniUcitelePrijmeni":"","referencedIdno":300892,"poznamkaRozvrhare":null,"nekonaSe":null,"owner":"RREHAKOVA","zakazaneAkce":null,"vyucJazyk":null}]}]