[{"rozvrhovaAkce":[{"roakIdno":278245,"nazev":"Paleontologie","katedra":"KBI","predmet":"K309","statut":"C","ucitIdno":1365,"ucitel":{"ucitIdno":1365,"jmeno":"Přemysl","prijmeni":"Zelenka","titulPred":"RNDr.","titulZa":"CSc.","platnost":"A","zamestnanec":"A"},"rok":"2016","budova":"ZV","mistnost":"B2","kapacitaMistnosti":12,"planObsazeni":10,"obsazeni":9,"typAkce":"Přednáška","typAkceZkr":"Př","semestr":"ZS","platnost":"A","den":"Sobota","denZkr":"So","hodinaOd":3,"hodinaDo":5,"hodinaSkutOd":{"value":"09:00"},"hodinaSkutDo":{"value":"11:50"},"tydenOd":39,"tydenDo":39,"tyden":"Jiný","tydenZkr":"J","grupIdno":null,"jeNadrazena":"N","maNadrazenou":"N","kontakt":"Automaticky vygenerovaná apost. akce","krouzky":"2.BI bc K","casovaRada":"UJEP","datum":null,"datumOd":{"value":"1.10.2016"},"datumDo":{"value":"1.10.2016"},"druhAkce":"R","vsichniUciteleUcitIdno":"1365","vsichniUciteleJmenaTituly":"RNDr. Přemysl Zelenka, CSc.","vsichniUcitelePrijmeni":"Zelenka","referencedIdno":278245,"poznamkaRozvrhare":null,"nekonaSe":null,"owner":"PETRUSPRF","zakazaneAkce":null,"vyucJazyk":null},{"roakIdno":278246,"nazev":"Paleontologie","katedra":"KBI","predmet":"K309","statut":"C","ucitIdno":1365,"ucitel":{"ucitIdno":1365,"jmeno":"Přemysl","prijmeni":"Zelenka","titulPred":"RNDr.","titulZa":"CSc.","platnost":"A","zamestnanec":"A"},"rok":"2016","budova":"ZV","mistnost":"B2","kapacitaMistnosti":12,"planObsazeni":10,"obsazeni":9,"typAkce":"Cvičení","typAkceZkr":"Cv","semestr":"ZS","platnost":"A","den":"Sobota","denZkr":"So","hodinaOd":6,"hodinaDo":8,"hodinaSkutOd":{"value":"12:00"},"hodinaSkutDo":{"value":"14:50"},"tydenOd":39,"tydenDo":39,"tyden":"Jiný","tydenZkr":"J","grupIdno":null,"jeNadrazena":"N","maNadrazenou":"N","kontakt":"Automaticky vygenerovaná apost. akce","krouzky":"2.BI bc K","casovaRada":"UJEP","datum":null,"datumOd":{"value":"1.10.2016"},"datumDo":{"value":"1.10.2016"},"druhAkce":"R","vsichniUciteleUcitIdno":"1365","vsichniUciteleJmenaTituly":"RNDr. Přemysl Zelenka, CSc.","vsichniUcitelePrijmeni":"Zelenka","referencedIdno":278246,"poznamkaRozvrhare":null,"nekonaSe":null,"owner":"PETRUSPRF","zakazaneAkce":null,"vyucJazyk":null},{"roakIdno":278240,"nazev":"Fylogeneze a systém strunatců","katedra":"KBI","predmet":"K302","statut":"A","ucitIdno":5472,"ucitel":{"ucitIdno":5472,"jmeno":"Michal","prijmeni":"Němec","titulPred":"RNDr.","titulZa":"Ph.D.","platnost":"A","zamestnanec":"A"},"rok":"2016","budova":"ZV","mistnost":"B2","kapacitaMistnosti":12,"planObsazeni":10,"obsazeni":10,"typAkce":"Přednáška","typAkceZkr":"Př","semestr":"ZS","platnost":"A","den":"Sobota","denZkr":"So","hodinaOd":3,"hodinaDo":10,"hodinaSkutOd":{"value":"09:00"},"hodinaSkutDo":{"value":"16:50"},"tydenOd":40,"tydenDo":40,"tyden":"Jiný","tydenZkr":"J","grupIdno":null,"jeNadrazena":"N","maNadrazenou":"N","kontakt":"Automaticky vygenerovaná apost. akce","krouzky":"2.BI bc K","casovaRada":"UJEP","datum":null,"datumOd":{"value":"8.10.2016"},"datumDo":{"value":"8.10.2016"},"druhAkce":"R","vsichniUciteleUcitIdno":"5472","vsichniUciteleJmenaTituly":"RNDr. Michal Němec, Ph.D.","vsichniUcitelePrijmeni":"Němec","referencedIdno":278240,"poznamkaRozvrhare":null,"nekonaSe":null,"owner":"PETRUSPRF","zakazaneAkce":null,"vyucJazyk":null},{"roakIdno":278232,"nazev":"Biologie prokaryot a virů","katedra":"KBI","predmet":"K104","statut":"A","ucitIdno":930,"ucitel":{"ucitIdno":930,"jmeno":"Jan","prijmeni":"Ipser","titulPred":"RNDr.","titulZa":"CSc.","platnost":"A","zamestnanec":"A"},"rok":"2016","budova":"ZV","mistnost":"B","kapacitaMistnosti":45,"planObsazeni":25,"obsazeni":24,"typAkce":"Přednáška","typAkceZkr":"Př","semestr":"ZS","platnost":"A","den":"Sobota","denZkr":"So","hodinaOd":3,"hodinaDo":10,"hodinaSkutOd":{"value":"09:00"},"hodinaSkutDo":{"value":"16:50"},"tydenOd":41,"tydenDo":41,"tyden":"Jiný","tydenZkr":"J","grupIdno":null,"jeNadrazena":"N","maNadrazenou":"N","kontakt":"Automaticky vygenerovaná apost. akce","krouzky":"1.BI JO KS","casovaRada":"UJEP","datum":null,"datumOd":{"value":"15.10.2016"},"datumDo":{"value":"15.10.2016"},"druhAkce":"R","vsichniUciteleUcitIdno":"930","vsichniUciteleJmenaTituly":"RNDr. Jan Ipser, CSc.","vsichniUcitelePrijmeni":"Ipser","referencedIdno":278232,"poznamkaRozvrhare":null,"nekonaSe":null,"owner":"PETRUSPRF","zakazaneAkce":null,"vyucJazyk":null},{"roakIdno":278243,"nazev":"Obecná parazitologie","katedra":"KBI","predmet":"K304","statut":"A","ucitIdno":1546,"ucitel":{"ucitIdno":1546,"jmeno":"Karina","prijmeni":"Vašinová","titulPred":"Mgr.","titulZa":"Ph.D.","platnost":"A","zamestnanec":"A"},"rok":"2016","budova":"ZV","mistnost":"B2","kapacitaMistnosti":12,"planObsazeni":10,"obsazeni":8,"typAkce":"Přednáška","typAkceZkr":"Př","semestr":"ZS","platnost":"A","den":"Sobota","denZkr":"So","hodinaOd":3,"hodinaDo":8,"hodinaSkutOd":{"value":"09:00"},"hodinaSkutDo":{"value":"14:50"},"tydenOd":41,"tydenDo":41,"tyden":"Jiný","tydenZkr":"J","grupIdno":null,"jeNadrazena":"N","maNadrazenou":"N","kontakt":"Automaticky vygenerovaná apost. akce","krouzky":"2.BI bc K","casovaRada":"UJEP","datum":null,"datumOd":{"value":"15.10.2016"},"datumDo":{"value":"15.10.2016"},"druhAkce":"R","vsichniUciteleUcitIdno":"1546","vsichniUciteleJmenaTituly":"Mgr. Karina Vašinová, Ph.D.","vsichniUcitelePrijmeni":"Vašinová","referencedIdno":278243,"poznamkaRozvrhare":null,"nekonaSe":null,"owner":"PETRUSPRF","zakazaneAkce":null,"vyucJazyk":null},{"roakIdno":278238,"nazev":"Fylogeneze a systém nižších rostlin","katedra":"KBI","predmet":"K301","statut":"A","ucitIdno":283,"ucitel":{"ucitIdno":283,"jmeno":"Lenka","prijmeni":"Němcová","titulPred":"RNDr.","titulZa":"CSc.","platnost":"A","zamestnanec":"A"},"rok":"2016","budova":"ZV","mistnost":"B1","kapacitaMistnosti":18,"planObsazeni":15,"obsazeni":12,"typAkce":"Přednáška","typAkceZkr":"Př","semestr":"ZS","platnost":"A","den":"Sobota","denZkr":"So","hodinaOd":3,"hodinaDo":8,"hodinaSkutOd":{"value":"09:00"},"hodinaSkutDo":{"value":"14:50"},"tydenOd":42,"tydenDo":42,"tyden":"Jiný","tydenZkr":"J","grupIdno":null,"jeNadrazena":"N","maNadrazenou":"N","kontakt":"Automaticky vygenerovaná apost. akce","krouzky":"2.BI bc K","casovaRada":"UJEP","datum":null,"datumOd":{"value":"22.10.2016"},"datumDo":{"value":"22.10.2016"},"druhAkce":"R","vsichniUciteleUcitIdno":"283","vsichniUciteleJmenaTituly":"RNDr. Lenka Němcová, CSc.","vsichniUcitelePrijmeni":"Němcová","referencedIdno":278238,"poznamkaRozvrhare":null,"nekonaSe":null,"owner":"PETRUSPRF","zakazaneAkce":null,"vyucJazyk":null},{"roakIdno":278244,"nazev":"Obecná parazitologie","katedra":"KBI","predmet":"K304","statut":"A","ucitIdno":1546,"ucitel":{"ucitIdno":1546,"jmeno":"Karina","prijmeni":"Vašinová","titulPred":"Mgr.","titulZa":"Ph.D.","platnost":"A","zamestnanec":"A"},"rok":"2016","budova":"ZV","mistnost":"B2","kapacitaMistnosti":12,"planObsazeni":10,"obsazeni":8,"typAkce":"Cvičení","typAkceZkr":"Cv","semestr":"ZS","platnost":"A","den":"Sobota","denZkr":"So","hodinaOd":3,"hodinaDo":8,"hodinaSkutOd":{"value":"09:00"},"hodinaSkutDo":{"value":"14:50"},"tydenOd":43,"tydenDo":43,"tyden":"Jiný","tydenZkr":"J","grupIdno":null,"jeNadrazena":"N","maNadrazenou":"N","kontakt":"Automaticky vygenerovaná apost. akce","krouzky":"2.BI bc K","casovaRada":"UJEP","datum":null,"datumOd":{"value":"29.10.2016"},"datumDo":{"value":"29.10.2016"},"druhAkce":"R","vsichniUciteleUcitIdno":"1546","vsichniUciteleJmenaTituly":"Mgr. Karina Vašinová, Ph.D.","vsichniUcitelePrijmeni":"Vašinová","referencedIdno":278244,"poznamkaRozvrhare":null,"nekonaSe":null,"owner":"PETRUSPRF","zakazaneAkce":null,"vyucJazyk":null},{"roakIdno":278239,"nazev":"Fylogeneze a systém nižších rostlin","katedra":"KBI","predmet":"K301","statut":"A","ucitIdno":283,"ucitel":{"ucitIdno":283,"jmeno":"Lenka","prijmeni":"Němcová","titulPred":"RNDr.","titulZa":"CSc.","platnost":"A","zamestnanec":"A"},"rok":"2016","budova":"ZV","mistnost":"B1","kapacitaMistnosti":18,"planObsazeni":15,"obsazeni":12,"typAkce":"Cvičení","typAkceZkr":"Cv","semestr":"ZS","platnost":"A","den":"Sobota","denZkr":"So","hodinaOd":3,"hodinaDo":9,"hodinaSkutOd":{"value":"09:00"},"hodinaSkutDo":{"value":"15:50"},"tydenOd":44,"tydenDo":44,"tyden":"Jiný","tydenZkr":"J","grupIdno":14113,"jeNadrazena":"N","maNadrazenou":"N","kontakt":"Automaticky vygenerovaná apost. akce","krouzky":"2.BI bc K","casovaRada":"UJEP","datum":null,"datumOd":{"value":"5.11.2016"},"datumDo":{"value":"5.11.2016"},"druhAkce":"R","vsichniUciteleUcitIdno":"283","vsichniUciteleJmenaTituly":"RNDr. Lenka Němcová, CSc.","vsichniUcitelePrijmeni":"Němcová","referencedIdno":278239,"poznamkaRozvrhare":null,"nekonaSe":null,"owner":"PETRUSPRF","zakazaneAkce":null,"vyucJazyk":null},{"roakIdno":278241,"nazev":"Fylogeneze a systém strunatců","katedra":"KBI","predmet":"K302","statut":"A","ucitIdno":5472,"ucitel":{"ucitIdno":5472,"jmeno":"Michal","prijmeni":"Němec","titulPred":"RNDr.","titulZa":"Ph.D.","platnost":"A","zamestnanec":"A"},"rok":"2016","budova":"ZV","mistnost":"B2","kapacitaMistnosti":12,"planObsazeni":10,"obsazeni":10,"typAkce":"Cvičení","typAkceZkr":"Cv","semestr":"ZS","platnost":"A","den":"Sobota","denZkr":"So","hodinaOd":3,"hodinaDo":10,"hodinaSkutOd":{"value":"09:00"},"hodinaSkutDo":{"value":"16:50"},"tydenOd":46,"tydenDo":46,"tyden":"Jiný","tydenZkr":"J","grupIdno":14112,"jeNadrazena":"N","maNadrazenou":"N","kontakt":"Automaticky vygenerovaná apost. akce","krouzky":"2.BI bc K","casovaRada":"UJEP","datum":null,"datumOd":{"value":"19.11.2016"},"datumDo":{"value":"19.11.2016"},"druhAkce":"R","vsichniUciteleUcitIdno":"5472","vsichniUciteleJmenaTituly":"RNDr. Michal Němec, Ph.D.","vsichniUcitelePrijmeni":"Němec","referencedIdno":278241,"poznamkaRozvrhare":null,"nekonaSe":null,"owner":"PETRUSPRF","zakazaneAkce":null,"vyucJazyk":null},{"roakIdno":278233,"nazev":"Biologie prokaryot a virů","katedra":"KBI","predmet":"K104","statut":"A","ucitIdno":930,"ucitel":{"ucitIdno":930,"jmeno":"Jan","prijmeni":"Ipser","titulPred":"RNDr.","titulZa":"CSc.","platnost":"A","zamestnanec":"A"},"rok":"2016","budova":"ZV","mistnost":"B1","kapacitaMistnosti":18,"planObsazeni":25,"obsazeni":24,"typAkce":"Cvičení","typAkceZkr":"Cv","semestr":"ZS","platnost":"A","den":"Sobota","denZkr":"So","hodinaOd":3,"hodinaDo":10,"hodinaSkutOd":{"value":"09:00"},"hodinaSkutDo":{"value":"16:50"},"tydenOd":48,"tydenDo":48,"tyden":"Jiný","tydenZkr":"J","grupIdno":null,"jeNadrazena":"N","maNadrazenou":"N","kontakt":"Automaticky vygenerovaná apost. akce","krouzky":"1.BI JO KS","casovaRada":"UJEP","datum":null,"datumOd":{"value":"3.12.2016"},"datumDo":{"value":"3.12.2016"},"druhAkce":"R","vsichniUciteleUcitIdno":"930","vsichniUciteleJmenaTituly":"RNDr. Jan Ipser, CSc.","vsichniUcitelePrijmeni":"Ipser","referencedIdno":278233,"poznamkaRozvrhare":null,"nekonaSe":null,"owner":"PETRUSPRF","zakazaneAkce":null,"vyucJazyk":null},{"roakIdno":278242,"nazev":"Etologie živočichů","katedra":"KBI","predmet":"K303","statut":"A","ucitIdno":2939,"ucitel":{"ucitIdno":2939,"jmeno":"Eva","prijmeni":"Jozífková","titulPred":"doc. RNDr.","titulZa":"Ph.D.","platnost":"A","zamestnanec":"A"},"rok":"2016","budova":"ZV","mistnost":"B2","kapacitaMistnosti":12,"planObsazeni":10,"obsazeni":9,"typAkce":"Přednáška","typAkceZkr":"Př","semestr":"ZS","platnost":"A","den":"Sobota","denZkr":"So","hodinaOd":3,"hodinaDo":6,"hodinaSkutOd":{"value":"09:00"},"hodinaSkutDo":{"value":"12:50"},"tydenOd":49,"tydenDo":49,"tyden":"Jiný","tydenZkr":"J","grupIdno":null,"jeNadrazena":"N","maNadrazenou":"N","kontakt":"Automaticky vygenerovaná apost. akce","krouzky":"2.BI bc K","casovaRada":"UJEP","datum":null,"datumOd":{"value":"10.12.2016"},"datumDo":{"value":"10.12.2016"},"druhAkce":"R","vsichniUciteleUcitIdno":"2939","vsichniUciteleJmenaTituly":"doc. RNDr. Eva Jozífková, Ph.D.","vsichniUcitelePrijmeni":"Jozífková","referencedIdno":278242,"poznamkaRozvrhare":null,"nekonaSe":null,"owner":"PETRUSPRF","zakazaneAkce":null,"vyucJazyk":null},{"roakIdno":278327,"nazev":"Fylogeneze a systém strunatců","katedra":"KBI","predmet":"K302","statut":"A","ucitIdno":5472,"ucitel":{"ucitIdno":5472,"jmeno":"Michal","prijmeni":"Němec","titulPred":"RNDr.","titulZa":"Ph.D.","platnost":"A","zamestnanec":"A"},"rok":"2016","budova":"ZV","mistnost":"B2","kapacitaMistnosti":12,"planObsazeni":10,"obsazeni":10,"typAkce":"Cvičení","typAkceZkr":"Cv","semestr":"ZS","platnost":"A","den":"Sobota","denZkr":"So","hodinaOd":7,"hodinaDo":10,"hodinaSkutOd":{"value":"13:00"},"hodinaSkutDo":{"value":"16:50"},"tydenOd":49,"tydenDo":49,"tyden":"Jiný","tydenZkr":"J","grupIdno":14112,"jeNadrazena":"N","maNadrazenou":"N","kontakt":"Automaticky vygenerovaná apost. akce","krouzky":"2.BI bc K","casovaRada":"UJEP","datum":null,"datumOd":{"value":"10.12.2016"},"datumDo":{"value":"10.12.2016"},"druhAkce":"R","vsichniUciteleUcitIdno":"5472","vsichniUciteleJmenaTituly":"RNDr. Michal Němec, Ph.D.","vsichniUcitelePrijmeni":"Němec","referencedIdno":278327,"poznamkaRozvrhare":null,"nekonaSe":null,"owner":"PETRUSPRF","zakazaneAkce":null,"vyucJazyk":null},{"roakIdno":278328,"nazev":"Fylogeneze a systém nižších rostlin","katedra":"KBI","predmet":"K301","statut":"A","ucitIdno":283,"ucitel":{"ucitIdno":283,"jmeno":"Lenka","prijmeni":"Němcová","titulPred":"RNDr.","titulZa":"CSc.","platnost":"A","zamestnanec":"A"},"rok":"2016","budova":"ZV","mistnost":"B2","kapacitaMistnosti":12,"planObsazeni":15,"obsazeni":12,"typAkce":"Cvičení","typAkceZkr":"Cv","semestr":"ZS","platnost":"A","den":"Sobota","denZkr":"So","hodinaOd":3,"hodinaDo":9,"hodinaSkutOd":{"value":"09:00"},"hodinaSkutDo":{"value":"15:50"},"tydenOd":50,"tydenDo":50,"tyden":"Jiný","tydenZkr":"J","grupIdno":14113,"jeNadrazena":"N","maNadrazenou":"N","kontakt":null,"krouzky":"2.BI bc K","casovaRada":"UJEP","datum":null,"datumOd":{"value":"17.12.2016"},"datumDo":{"value":"17.12.2016"},"druhAkce":"R","vsichniUciteleUcitIdno":"283","vsichniUciteleJmenaTituly":"RNDr. Lenka Němcová, CSc.","vsichniUcitelePrijmeni":"Němcová","referencedIdno":278328,"poznamkaRozvrhare":null,"nekonaSe":null,"owner":"PETRUSPRF","zakazaneAkce":null,"vyucJazyk":null},{"roakIdno":292714,"nazev":"IT v biologických vědách II","katedra":"KBI","predmet":"KICT2","statut":"B","ucitIdno":null,"ucitel":null,"rok":"2016","budova":null,"mistnost":null,"kapacitaMistnosti":null,"planObsazeni":777,"obsazeni":3,"typAkce":"Cvičení","typAkceZkr":"Cv","semestr":"ZS","platnost":"A","den":null,"denZkr":null,"hodinaOd":null,"hodinaDo":null,"hodinaSkutOd":{"value":"00:00"},"hodinaSkutDo":{"value":"00:00"},"tydenOd":0,"tydenDo":0,"tyden":"Každý","tydenZkr":"K","grupIdno":null,"jeNadrazena":"N","maNadrazenou":"N","kontakt":"Automaticky vygenerovaná apost. akce","krouzky":null,"casovaRada":null,"datum":null,"datumOd":null,"datumDo":null,"druhAkce":"R","vsichniUciteleUcitIdno":"","vsichniUciteleJmenaTituly":"","vsichniUcitelePrijmeni":"","referencedIdno":292714,"poznamkaRozvrhare":null,"nekonaSe":null,"owner":"PETRUSPRF","zakazaneAkce":null,"vyucJazyk":null},{"roakIdno":292715,"nazev":"Environmentální legislativa","katedra":"KBI","predmet":"K305","statut":"A","ucitIdno":null,"ucitel":null,"rok":"2016","budova":null,"mistnost":null,"kapacitaMistnosti":null,"planObsazeni":777,"obsazeni":1,"typAkce":"Cvičení","typAkceZkr":"Cv","semestr":"ZS","platnost":"A","den":null,"denZkr":null,"hodinaOd":null,"hodinaDo":null,"hodinaSkutOd":{"value":"00:00"},"hodinaSkutDo":{"value":"00:00"},"tydenOd":0,"tydenDo":0,"tyden":"Každý","tydenZkr":"K","grupIdno":null,"jeNadrazena":"N","maNadrazenou":"N","kontakt":"Automaticky vygenerovaná apost. akce","krouzky":null,"casovaRada":null,"datum":null,"datumOd":null,"datumDo":null,"druhAkce":"R","vsichniUciteleUcitIdno":"","vsichniUciteleJmenaTituly":"","vsichniUcitelePrijmeni":"","referencedIdno":292715,"poznamkaRozvrhare":null,"nekonaSe":null,"owner":"PETRUSPRF","zakazaneAkce":null,"vyucJazyk":null},{"roakIdno":292716,"nazev":"PVK - Limnobiologie","katedra":"KBI","predmet":"K307","statut":"B","ucitIdno":null,"ucitel":null,"rok":"2016","budova":null,"mistnost":null,"kapacitaMistnosti":null,"planObsazeni":777,"obsazeni":1,"typAkce":"Cvičení","typAkceZkr":"Cv","semestr":"ZS","platnost":"A","den":null,"denZkr":null,"hodinaOd":null,"hodinaDo":null,"hodinaSkutOd":{"value":"00:00"},"hodinaSkutDo":{"value":"00:00"},"tydenOd":0,"tydenDo":0,"tyden":"Každý","tydenZkr":"K","grupIdno":null,"jeNadrazena":"N","maNadrazenou":"N","kontakt":"Automaticky vygenerovaná apost. akce","krouzky":null,"casovaRada":null,"datum":null,"datumOd":null,"datumDo":null,"druhAkce":"R","vsichniUciteleUcitIdno":"","vsichniUciteleJmenaTituly":"","vsichniUcitelePrijmeni":"","referencedIdno":292716,"poznamkaRozvrhare":null,"nekonaSe":null,"owner":"PETRUSPRF","zakazaneAkce":null,"vyucJazyk":null},{"roakIdno":292717,"nazev":"Vývoj a stavba vesmíru","katedra":"KFY","predmet":"K308","statut":"A","ucitIdno":null,"ucitel":null,"rok":"2016","budova":null,"mistnost":null,"kapacitaMistnosti":null,"planObsazeni":777,"obsazeni":1,"typAkce":"Přednáška","typAkceZkr":"Př","semestr":"ZS","platnost":"A","den":null,"denZkr":null,"hodinaOd":null,"hodinaDo":null,"hodinaSkutOd":{"value":"00:00"},"hodinaSkutDo":{"value":"00:00"},"tydenOd":0,"tydenDo":0,"tyden":"Každý","tydenZkr":"K","grupIdno":null,"jeNadrazena":"N","maNadrazenou":"N","kontakt":"Automaticky vygenerovaná apost. akce","krouzky":null,"casovaRada":null,"datum":null,"datumOd":null,"datumDo":null,"druhAkce":"R","vsichniUciteleUcitIdno":"","vsichniUciteleJmenaTituly":"","vsichniUcitelePrijmeni":"","referencedIdno":292717,"poznamkaRozvrhare":null,"nekonaSe":null,"owner":"PETRUSPRF","zakazaneAkce":null,"vyucJazyk":null},{"roakIdno":292718,"nazev":"Vývoj a stavba vesmíru","katedra":"KFY","predmet":"K308","statut":"A","ucitIdno":null,"ucitel":null,"rok":"2016","budova":null,"mistnost":null,"kapacitaMistnosti":null,"planObsazeni":777,"obsazeni":1,"typAkce":"Cvičení","typAkceZkr":"Cv","semestr":"ZS","platnost":"A","den":null,"denZkr":null,"hodinaOd":null,"hodinaDo":null,"hodinaSkutOd":{"value":"00:00"},"hodinaSkutDo":{"value":"00:00"},"tydenOd":0,"tydenDo":0,"tyden":"Každý","tydenZkr":"K","grupIdno":null,"jeNadrazena":"N","maNadrazenou":"N","kontakt":"Automaticky vygenerovaná apost. akce","krouzky":null,"casovaRada":null,"datum":null,"datumOd":null,"datumDo":null,"druhAkce":"R","vsichniUciteleUcitIdno":"","vsichniUciteleJmenaTituly":"","vsichniUcitelePrijmeni":"","referencedIdno":292718,"poznamkaRozvrhare":null,"nekonaSe":null,"owner":"PETRUSPRF","zakazaneAkce":null,"vyucJazyk":null},{"roakIdno":295930,"nazev":"Kryptogamologické terénní cvičení","katedra":"KBI","predmet":"K205","statut":"A","ucitIdno":283,"ucitel":{"ucitIdno":283,"jmeno":"Lenka","prijmeni":"Němcová","titulPred":"RNDr.","titulZa":"CSc.","platnost":"A","zamestnanec":"A"},"rok":"2016","budova":null,"mistnost":null,"kapacitaMistnosti":null,"planObsazeni":15,"obsazeni":9,"typAkce":"Cvičení","typAkceZkr":"Cv","semestr":"LS","platnost":"A","den":"Sobota","denZkr":"So","hodinaOd":3,"hodinaDo":10,"hodinaSkutOd":{"value":"09:00"},"hodinaSkutDo":{"value":"16:50"},"tydenOd":19,"tydenDo":19,"tyden":"Jiný","tydenZkr":"J","grupIdno":null,"jeNadrazena":"N","maNadrazenou":"N","kontakt":"Automaticky vygenerovaná apost. akce","krouzky":"2.BI bc K","casovaRada":"UJEP","datum":null,"datumOd":{"value":"13.5.2017"},"datumDo":{"value":"13.5.2017"},"druhAkce":"R","vsichniUciteleUcitIdno":"283","vsichniUciteleJmenaTituly":"RNDr. Lenka Němcová, CSc.","vsichniUcitelePrijmeni":"Němcová","referencedIdno":295930,"poznamkaRozvrhare":null,"nekonaSe":null,"owner":"RREHAKOVA","zakazaneAkce":null,"vyucJazyk":null}]}]